seqtrainer/__init__.py
seqtrainer/_autordf2gml-tb.py
seqtrainer/_autordf2gml.py
seqtrainer/config-helper.py
seqtrainer/dataset_builder.py
seqtrainer/gnn.py
seqtrainer/preprocessing.py
seqtrainer/pwm.py
seqtrainer-0.0.1.dist-info/licenses/LICENSE
seqtrainer-0.0.1.dist-info/METADATA
seqtrainer-0.0.1.dist-info/WHEEL
seqtrainer-0.0.1.dist-info/top_level.txt
seqtrainer-0.0.1.dist-info/RECORD
