Metadata-Version: 2.4
Name: seqtrainer
Version: 0.0.1
Summary: SeqTrainer: Encoding Synthetic Biology Data for Machine Learning
Author-email: Gonzalo Vidal <Gonzalo.VidalPena@colorado.edu>, Sai Wong <sai.wong@sjsu.edu>
Maintainer-email: Gonzalo Vidal <Gonzalo.VidalPena@colorado.edu>
License: MIT License
Project-URL: Homepage, https://github.com/SynBioDex/SeqTrainer
Project-URL: Bug Tracker, https://github.com/SynBioDex/SeqTrainer/issues
Keywords: seqtrainer,sbol,machine learning,preprocessing,synthetic biology
Classifier: Programming Language :: Python :: 3
Classifier: License :: OSI Approved :: MIT License
Classifier: Operating System :: OS Independent
Requires-Python: <=3.9.9,>=3.8
License-File: LICENSE
Requires-Dist: sbol2
Requires-Dist: matplotlib
Requires-Dist: rdflib==6.3.2
Requires-Dist: pandas==1.3.5
Requires-Dist: numpy==1.23.5
Requires-Dist: configparser==6.0.0
Requires-Dist: scikit-learn==1.3.0
Requires-Dist: transformers==4.30.2
Requires-Dist: tqdm==4.65.0
Provides-Extra: gnn
Requires-Dist: torch==1.13.0+cpu; extra == "gnn"
Requires-Dist: torch-geometric==2.4.0; extra == "gnn"
Dynamic: license-file
